{
  "pass": true,
  "generatedAt": "2026-07-21T05:33:04.486Z",
  "baseUrl": "http://127.0.0.1:3080",
  "checks": [
    {
      "name": "isolated permanent purge removes execution, TestAgent and replay evidence with audit receipt",
      "pass": true
    },
    {
      "name": "summary exposes storage, retention policy, quality evidence and cleanup history",
      "pass": true
    },
    {
      "name": "preview creates expiring exact snapshot without exposing internal fingerprints",
      "pass": true
    },
    {
      "name": "run API requires both explicit confirmation and a valid preview snapshot",
      "pass": true
    }
  ]
}